{
  "cli": {
    "version": ">= 7.0.0"
  },
  "build": {
    "development": {
      "developmentClient": true,
      "distribution": "internal",
      "env": {
        "NODE_ENV": "development"
      }
    },
    "preview": {
      "distribution": "internal",
      "env": {
        "NODE_ENV": "production"
      },
      "android": {
        "buildType": "apk"
      }
    },
    "production": {
      "env": {
        "NODE_ENV": "production"
      },
      "android": {
        "buildType": "apk",
        "gradleCommand": ":app:assembleRelease"
      },
      "ios": {
        "buildConfiguration": "Release"
      }
    }
  },
  "submit": {
    "production": {
      "android": {
        "serviceAccountKeyPath": "./android-service-account.json"
      },
      "ios": {}
    }
  }
}
